rero/__init__.py
rero/exceptions.py
rero/packer.py
rero-1.0.1.dist-info/LICENSE.md
rero-1.0.1.dist-info/WHEEL
rero-1.0.1.dist-info/METADATA
rero-1.0.1.dist-info/RECORD
