Metadata-Version: 2.1
Name: rero
Version: 1.0.1
Summary: Rero is a transmission protocol suitable for efficient, reliable, and robust communication especially well suited for DMA supported MCU operations.
Home-page: https://panir.gitlab.io/rero
License: MIT
Keywords: protocol,efficient,scalable,DMA,MCU
Author: Reinhard Panhuber
Requires-Python: >=3.5,<4.0
Classifier: License :: OSI Approved :: MIT License
Classifier: Programming Language :: Python :: 3
Classifier: Programming Language :: Python :: 3.5
Classifier: Programming Language :: Python :: 3.6
Classifier: Programming Language :: Python :: 3.7
Requires-Dist: cobs (>=1.1,<2.0)
Requires-Dist: crcmod (>=1.7,<2.0)
Project-URL: Documentation, https://panir.gitlab.io/rero
Project-URL: Repository, https://gitlab.com/PaniR/rero
